{
    "title": "Mission Control",
    "rules": [
        {
            "description": "[Mac]Move left a space(alt+command+h) / Move righ a space(alt+command+l)",
            "manipulators": [
                {
                    "type": "basic",
                    "from": {
                        "key_code": "h",
                        "modifiers": {
                            "mandatory": [
                                "option",
                                "command"
                            ],
                            "optional": [
                                "caps_lock"
                            ]
                        }
                    },
                    "to": [
                        {
                            "key_code": "left_arrow",
                            "modifiers": [
                                "left_option",
                                "left_command"
                            ]
                        }
                    ]
                },
                {
                    "type": "basic",
                    "from": {
                        "key_code": "l",
                        "modifiers": {
                            "mandatory": [
                                "option",
                                "command"
                            ],
                            "optional": [
                                "caps_lock"
                            ]
                        }
                    },
                    "to": [
                        {
                            "key_code": "right_arrow",
                            "modifiers": [
                                "left_option",
                                "left_command"
                            ]
                        }
                    ]
                }
            ]
        },
        {
            "description": "[PC]Move left a space(alt+ctrl+h) / Move righ a space(alt+ctrl+l)",
            "manipulators": [
                {
                    "type": "basic",
                    "from": {
                        "key_code": "h",
                        "modifiers": {
                            "mandatory": [
                                "option",
                                "control"
                            ],
                            "optional": [
                                "caps_lock"
                            ]
                        }
                    },
                    "to": [
                        {
                            "key_code": "left_arrow",
                            "modifiers": [
                                "left_option",
                                "left_command"
                            ]
                        }
                    ]
                },
                {
                    "type": "basic",
                    "from": {
                        "key_code": "l",
                        "modifiers": {
                            "mandatory": [
                                "option",
                                "control"
                            ],
                            "optional": [
                                "caps_lock"
                            ]
                        }
                    },
                    "to": [
                        {
                            "key_code": "right_arrow",
                            "modifiers": [
                                "left_option",
                                "left_command"
                            ]
                        }
                    ]
                }
            ]
        },
        {
            "description": "[PC]Move left a space(alt+ctrl+left) / Move righ a space(alt+ctrl+right)",
            "manipulators": [
                {
                    "type": "basic",
                    "from": {
                        "key_code": "left_arrow",
                        "modifiers": {
                            "mandatory": [
                                "option",
                                "control"
                            ],
                            "optional": [
                                "caps_lock"
                            ]
                        }
                    },
                    "to": [
                        {
                            "key_code": "left_arrow",
                            "modifiers": [
                                "left_option",
                                "left_command"
                            ]
                        }
                    ]
                },
                {
                    "type": "basic",
                    "from": {
                        "key_code": "right_arrow",
                        "modifiers": {
                            "mandatory": [
                                "option",
                                "control"
                            ],
                            "optional": [
                                "caps_lock"
                            ]
                        }
                    },
                    "to": [
                        {
                            "key_code": "right_arrow",
                            "modifiers": [
                                "left_option",
                                "left_command"
                            ]
                        }
                    ]
                }
            ]
        }
    ]
}